candle/__init__.py
candle/config.py
candle/callbacks/__init__.py
candle/callbacks/base.py
candle/callbacks/console_logger.py
candle/callbacks/early_stopping.py
candle/callbacks/lr_handlers.py
candle/callbacks/not_implemented.py
candle/datasets/__init__.py
candle/development/__init__.py
candle/development/warnings.py
candle/metrics/__init__.py
candle/metrics/base.py
candle/metrics/classificaation.py
candle/metrics/regression.py
candle/models/__init__.py
candle/models/language/__init__.py
candle/models/multimodal/__init__.py
candle/models/vision/__init__.py
candle/models/vision/basic_cnn.py
candle/models/vision/resnet18.py
candle/trainers/__init__.py
candle/trainers/base.py
candle/trainers/template.py
candle/trainers/trainer.py
candle/utils/__init__.py
candle/utils/module.py
candle/utils/tracking.py
tests/__init__.py
tests/test_callbacks.py
tests/test_metrics.py
tests/test_trainer.py
tests/test_utils.py
pytorch_candle-0.0.18.dist-info/LICENSE
pytorch_candle-0.0.18.dist-info/METADATA
pytorch_candle-0.0.18.dist-info/WHEEL
pytorch_candle-0.0.18.dist-info/top_level.txt
pytorch_candle-0.0.18.dist-info/RECORD
